mkdocs_vercel_pw_plugin/__init__.py
mkdocs_vercel_pw_plugin/deployment_forbidden.html
mkdocs_vercel_pw_plugin/deployment_not_found.html
mkdocs_vercel_pw_plugin/logout.html
mkdocs_vercel_pw_plugin-0.1.0.dist-info/LICENSE
mkdocs_vercel_pw_plugin-0.1.0.dist-info/METADATA
mkdocs_vercel_pw_plugin-0.1.0.dist-info/WHEEL
mkdocs_vercel_pw_plugin-0.1.0.dist-info/entry_points.txt
mkdocs_vercel_pw_plugin-0.1.0.dist-info/top_level.txt
mkdocs_vercel_pw_plugin-0.1.0.dist-info/RECORD
