Metadata-Version: 2.1
Name: mkdocs-vercel-pw-plugin
Version: 0.1.0
Summary: Add routes to your vercel.json that enforces password authentication
Home-page: https://github.com/six-two/mkdocs-vercel-pw-plugin
Author: six-two
Author-email: pip@six-two.dev
License: MIT License
Classifier: License :: OSI Approved :: MIT License
Classifier: Operating System :: POSIX :: Linux
Classifier: Programming Language :: Python :: 3
Classifier: Programming Language :: Python :: 3.9
Classifier: Programming Language :: Python :: 3.10
Classifier: Programming Language :: Python :: 3.11
Requires-Python: >=3.9
License-File: LICENSE
Requires-Dist: mkdocs >=1.5.0
